my_cli_project/__init__.py
my_cli_project/cli.py
my_cli_project/utils.py
my_cli_project-0.0.1.dist-info/entry_points.txt
my_cli_project-0.0.1.dist-info/METADATA
my_cli_project-0.0.1.dist-info/WHEEL
my_cli_project-0.0.1.dist-info/RECORD
