Metadata-Version: 2.3
Name: my_cli_project
Version: 0.0.1
Summary: A sample Poetry project with a CLI and custom Python code
Author: Your Name
Author-email: ian@example.com
Requires-Python: >=3.8,<4.0
Classifier: Programming Language :: Python :: 3
Classifier: Programming Language :: Python :: 3.8
Classifier: Programming Language :: Python :: 3.9
Classifier: Programming Language :: Python :: 3.10
Classifier: Programming Language :: Python :: 3.11
Classifier: Programming Language :: Python :: 3.12
Classifier: Programming Language :: Python :: 3.13
Requires-Dist: click (>=8.1.3,<9.0.0)
Requires-Dist: requests (>=2.32.3,<3.0.0)
